sparrow_parse/__init__.py
sparrow_parse/__main__.py
sparrow_parse/test_extraction_mlx.py
sparrow_parse/test_extraction_ollama.py
sparrow_parse/extractors/__init__.py
sparrow_parse/extractors/vllm_extractor.py
sparrow_parse/helpers/__init__.py
sparrow_parse/helpers/image_optimizer.py
sparrow_parse/helpers/pdf_optimizer.py
sparrow_parse/processors/__init__.py
sparrow_parse/processors/table_structure_processor.py
sparrow_parse/vllm/__init__.py
sparrow_parse/vllm/huggingface_inference.py
sparrow_parse/vllm/inference_base.py
sparrow_parse/vllm/inference_factory.py
sparrow_parse/vllm/local_gpu_inference.py
sparrow_parse/vllm/mlx_inference.py
sparrow_parse/vllm/ollama_inference.py
sparrow_parse-1.2.3.dist-info/METADATA
sparrow_parse-1.2.3.dist-info/WHEEL
sparrow_parse-1.2.3.dist-info/entry_points.txt
sparrow_parse-1.2.3.dist-info/top_level.txt
sparrow_parse-1.2.3.dist-info/RECORD
