Metadata-Version: 2.4
Name: sparrow-parse
Version: 1.2.3
Summary: Sparrow Parse is a Python package (part of Sparrow) for parsing and extracting information from documents.
Home-page: https://github.com/katanaml/sparrow/tree/main/sparrow-data/parse
Author: Andrej Baranovskij
Author-email: andrejus.baranovskis@gmail.com
Project-URL: Homepage, https://github.com/katanaml/sparrow/tree/main/sparrow-data/parse
Project-URL: Repository, https://github.com/katanaml/sparrow
Keywords: llm,vllm,ocr,vision
Classifier: Operating System :: OS Independent
Classifier: License :: OSI Approved :: GNU General Public License v3 (GPLv3)
Classifier: Topic :: Software Development
Classifier: Programming Language :: Python :: 3.10
Requires-Python: >=3.12
Requires-Dist: rich
Requires-Dist: transformers==4.57.3
Requires-Dist: torchvision==0.24.1
Requires-Dist: torch==2.9.1
Requires-Dist: sentence-transformers==5.2.0
Requires-Dist: numpy==2.2.6
Requires-Dist: pypdf==6.4.2
Requires-Dist: gradio_client==2.0.1
Requires-Dist: pdf2image==1.17.0
Requires-Dist: ollama==0.6.1
Provides-Extra: mlx
Requires-Dist: mlx==0.30.0; (sys_platform == "darwin" and platform_machine == "arm64") and extra == "mlx"
Requires-Dist: mlx-vlm==0.3.9; (sys_platform == "darwin" and platform_machine == "arm64") and extra == "mlx"
Provides-Extra: all
Requires-Dist: mlx==0.30.0; (sys_platform == "darwin" and platform_machine == "arm64") and extra == "all"
Requires-Dist: mlx-vlm==0.3.9; (sys_platform == "darwin" and platform_machine == "arm64") and extra == "all"
Dynamic: author
Dynamic: author-email
Dynamic: classifier
Dynamic: description
Dynamic: description-content-type
Dynamic: home-page
Dynamic: keywords
Dynamic: project-url
Dynamic: provides-extra
Dynamic: requires-dist
Dynamic: requires-python
Dynamic: summary
